[
    {
        "title": "ІФТехСервіс",
        "icon-file": "icon-custom-ifts.png",
        "description": "ІФТехСервіс &mdash; про нас",
        "content-file": "about-us.html"
    },
    {
        "title": "Де і як нас знайти",
        "icon-class": "fa-map-marker",
        "description": "Де і як нас знайти",
        "content-file": "map.html"
    },
    {
        "title": "Фото",
        "icon-class": "fa-photo",
        "description": "Краще раз побачити",
        "content-file": "photo.html"
    },
    {
        "title": "Ми у Facebook",
        "icon-class": "fa-facebook-square",
        "description": "Група у Facebook &mdash; тут можна поговорити з нами",
        "content-file": "facebook.html"
    },
    {
        "title": "Наш Youtube-канал",
        "icon-class": "fa-youtube-square",
        "description": "Наш Youtube-канал",
        "link": "https://www.youtube.com/channel/UCt_yF8V7WIHnJ2-pGcI28dg"
    },
    {
        "title": "Ми на List.if.ua",
        "icon-file": "list-if-ua.png",
        "description": "List.if.ua — відгуки про нас",
        "link": "http://list.if.ua/54147/%D0%86%D0%A4%D0%A2%D0%B5%D1%85%D0%A1%D0%B5%D1%80%D0%B2%D1%96%D1%81-%D0%86%D0%B2%D0%B0%D0%BD%D0%BE-%D0%A4%D1%80%D0%B0%D0%BD%D0%BA%D1%96%D0%B2%D1%81%D1%8C%D0%BA"
    },
    {
        "title": "Ми на SkyLots",
        "icon-file": "skylots.png",
        "description": "Ми на SkyLots",
        "link": "https://skylots.org/search.php?seller_id=14323956&amp;catid=0&amp;orderby=2"
    },
    {
        "title": "Ми на NewAuction",
        "icon-file": "new-auction.png",
        "description": "Ми на NewAuction",
        "link": "https://newauction.com.ua/listing/offer/glavnaja-1?flt_prp_offerstate=0&amp;flt_prp_owner=14323956&amp;flt_prp_sesend=gt__macro_now&amp;flt_prp_sesstart=lt__macro_now&amp;srt_prp_cur_price=dsc&amp;ipp=60"
    },
    {
        "title": "Ми на Slando/OLX",
        "icon-file": "sladno.png",
        "description": "Ми на Slando/OLX",
        "link": "http://olx.ua/list/user/11VK1"
    },
    {
        "title": "Наші партнери",
        "icon-class": "fa-thumbs-up",
        "description": "Наші партнери",
        "content-file": "partners.html"
    }
]